sbx_emotions_kb_emoclass/__init__.py
sbx_emotions_kb_emoclass/annotations.py
sbx_emotions_kb_emoclass/constants.py
sbx_emotions_kb_emoclass/emotional_classifier.py
sbx_emotions_kb_emoclass/metadata.yaml
sbx_emotions_kb_emoclass/py.typed
sparv_sbx_emotions_kb_emoclass-0.1.1.dist-info/WHEEL
sparv_sbx_emotions_kb_emoclass-0.1.1.dist-info/entry_points.txt
sparv_sbx_emotions_kb_emoclass-0.1.1.dist-info/METADATA
sparv_sbx_emotions_kb_emoclass-0.1.1.dist-info/RECORD
