Metadata-Version: 2.3
Name: sparv-sbx-emotions-kb-emoclass
Version: 0.1.1
Summary: A sparv plugin for classificating emotions in Swedish text.
Author: Språkbanken Text
Author-email: Språkbanken Text <sb-info@svenska.gu.se>
Classifier: Development Status :: 4 - Beta
Classifier: Intended Audience :: Developers
Classifier: License :: OSI Approved :: MIT License
Classifier: Operating System :: Unix
Classifier: Operating System :: POSIX
Classifier: Programming Language :: Python :: 3.11
Classifier: Programming Language :: Python :: 3.12
Classifier: Programming Language :: Python :: Implementation :: CPython
Classifier: Topic :: Utilities
Requires-Dist: setfit>=1.1.3
Requires-Dist: sparv>=5.3.1
Requires-Dist: numpy>=1.24.4,<2.0.0
Requires-Dist: scikit-learn>=1.2.0,<1.3.0
Requires-Python: >=3.11
Project-URL: Bug Tracker, https://github.com/spraakbanken/sparv-sbx-emotions-kb-emoclass/issues
Project-URL: Homepage, https://spraakbanken.gu.se
Project-URL: Repository, https://github.com/spraakbanken/sparv-sbx-emotions-kb-emoclass
